{
  "data": [
    {
      "index": 1,
      "arabic_ayat": "وَٱلَّذِينَ ءَامَنُوا۟ وَعَمِلُوا۟ ٱلصَّـٰلِحَـٰتِ لَنُكَفِّرَنَّ عَنْهُمْ سَيِّـَٔاتِهِمْ وَلَنَجْزِيَنَّهُمْ أَحْسَنَ ٱلَّذِى كَانُوا۟ يَعْمَلُونَ",
      "urdu_ayat": "جو لوگ ایمان لائے اور نیک عمل کرتے رہے ہم ان کے گناہوں کو ضرور معاف کر دیں گے اور ان کو ان کے بہترین اعمال کے مطابق جزا دیں گے۔",
      "english_ayat": "But those who believe and do righteous deeds — We will surely remove from them their misdeeds and will reward them according to the best of what they used to do. (Al-Ankabut 29:7)"
    },
    {
      "index": 2,
      "arabic_ayat": "إِنَّ ٱللَّهَ مَعَ ٱلصَّـٰبِرِينَ",
      "urdu_ayat": "بے شک اللہ صبر کرنے والوں کے ساتھ ہے۔",
      "english_ayat": "Indeed, Allah is with the patient. (Al-Baqarah 2:153)"
    },
    {
      "index": 3,
      "arabic_ayat": "وَمَن يَتَوَكَّلْ عَلَى ٱللَّهِ فَهُوَ حَسْبُهُۥٓ",
      "urdu_ayat": "اور جو اللہ پر بھروسہ کرے تو وہ اس کے لیے کافی ہے۔",
      "english_ayat": "And whoever relies upon Allah — then He is sufficient for him. (At-Talaq 65:3)"
    },
    {
      "index": 4,
      "arabic_ayat": "فَإِنَّ مَعَ ٱلْعُسْرِ يُسْرًا إِنَّ مَعَ ٱلْعُسْرِ يُسْرًا",
      "urdu_ayat": "پس بے شک تکلیف کے ساتھ آسانی ہے، بے شک تکلیف کے ساتھ آسانی ہے۔",
      "english_ayat": "For indeed, with hardship will be ease. Indeed, with hardship will be ease. (Ash-Sharh 94:5-6)"
    },
    {
      "index": 5,
      "arabic_ayat": "وَلَا تَيْأَسُوا۟ مِن رَّوْحِ ٱللَّهِ ۖ إِنَّهُۥ لَا يَيْأَسُ مِن رَّوْحِ ٱللَّهِ إِلَّا ٱلْقَوْمُ ٱلْكَـٰفِرُونَ",
      "urdu_ayat": "اور اللہ کی رحمت سے مایوس نہ ہو، بے شک اللہ کی رحمت سے صرف کافر لوگ ہی مایوس ہوتے ہیں۔",
      "english_ayat": "And do not despair of relief from Allah. Indeed, no one despairs of relief from Allah except the disbelieving people. (Yusuf 12:87)"
    },
    {
      "index": 6,
      "arabic_ayat": "رَبَّنَآ ءَاتِنَا فِى ٱلدُّنْيَا حَسَنَةً وَفِى ٱلْـَٔاخِرَةِ حَسَنَةً وَقِنَا عَذَابَ ٱلنَّارِ",
      "urdu_ayat": "اے ہمارے رب! ہمیں دنیا میں بھلائی عطا فرما اور آخرت میں بھی بھلائی عطا فرما اور ہمیں آگ کے عذاب سے بچا۔",
      "english_ayat": "Our Lord, give us in this world good and in the Hereafter good and protect us from the punishment of the Fire. (Al-Baqarah 2:201)"
    },
    {
      "index": 7,
      "arabic_ayat": "ٱللَّهُ لَآ إِلَـٰهَ إِلَّا هُوَ ٱلْحَىُّ ٱلْقَيُّومُ",
      "urdu_ayat": "اللہ، اس کے سوا کوئی معبود نہیں، وہ زندہ ہے، ہمیشہ قائم رہنے والا ہے۔",
      "english_ayat": "Allah — there is no deity except Him, the Ever-Living, the Sustainer of existence. (Al-Baqarah 2:255)"
    },
    {
      "index": 8,
      "arabic_ayat": "وَٱذْكُر رَّبَّكَ كَثِيرًا وَسَبِّحْ بِٱلْعَشِىِّ وَٱلْإِبْكَـٰرِ",
      "urdu_ayat": "اور اپنے رب کو کثرت سے یاد کرو اور شام اور صبح اس کی تسبیح کرو۔",
      "english_ayat": "And remember your Lord much and exalt Him in the evening and the morning. (Ali 'Imran 3:41)"
    },
    {
      "index": 9,
      "arabic_ayat": "إِنَّ ٱللَّهَ لَا يُغَيِّرُ مَا بِقَوْمٍ حَتَّىٰ يُغَيِّرُوا۟ مَا بِأَنفُسِهِمْ",
      "urdu_ayat": "بے شک اللہ کسی قوم کی حالت نہیں بدلتا جب تک وہ خود اپنی حالت نہ بدلیں۔",
      "english_ayat": "Indeed, Allah will not change the condition of a people until they change what is in themselves. (Ar-Ra'd 13:11)"
    },
    {
      "index": 10,
      "arabic_ayat": "وَقُل رَّبِّ زِدْنِى عِلْمًا",
      "urdu_ayat": "اور کہو: اے میرے رب! مجھے علم میں اضافہ عطا فرما۔",
      "english_ayat": "And say: My Lord, increase me in knowledge. (Ta-Ha 20:114)"
    }
  ]
}
